monicapf/__init__.py
monicapf/app.py
monicapf/middleware.py
monicapf/response.py
monicapf-0.1.4.dist-info/METADATA
monicapf-0.1.4.dist-info/WHEEL
monicapf-0.1.4.dist-info/top_level.txt
monicapf-0.1.4.dist-info/RECORD
