Metadata-Version: 2.1
Name: monicapf
Version: 0.1.4
Summary: Python Web Frmaework built for learning purposes. 
Home-page: https://github.com/me/myproject
Author: Abdumalikov Bilolbek
Author-email: bilolabdumalikov1@gmail.com
License: MIT
Platform: UNKNOWN
Classifier: License :: OSI Approved :: MIT License
Classifier: Programming Language :: Python
Classifier: Programming Language :: Python :: 3
Classifier: Programming Language :: Python :: 3.9
Classifier: Programming Language :: Python :: Implementation :: CPython
Classifier: Programming Language :: Python :: Implementation :: PyPy
Requires-Python: >=3.9.0
Requires-Dist: gunicorn ==19.9.0
Requires-Dist: Jinja2 ==3.1.4
Requires-Dist: whitenoise ==6.6.0
Requires-Dist: WebOb ==1.8.5
Requires-Dist: parse ==1.11.1
Requires-Dist: requests ==2.31.0
Requires-Dist: requests-wsgi-adapter ==0.4.0
